turingnetwork/__init__.py
turingnetwork/backend/cli.py
turingnetwork/backend/config.py
turingnetwork/backend/server.py
turingnetwork/backend/utility.py
turingnetwork/client/flmap.py
turingnetwork/client/main.py
turingnetwork/client/python_tracer.py
turingnetwork-0.1.1.dist-info/LICENSE.txt
turingnetwork-0.1.1.dist-info/METADATA
turingnetwork-0.1.1.dist-info/RECORD
turingnetwork-0.1.1.dist-info/WHEEL
turingnetwork-0.1.1.dist-info/entry_points.txt
turingnetwork-0.1.1.dist-info/top_level.txt
